{
  "entry":{
    "description":"0, -8"
  },
  "lastVisit":{
    "Bob":1506050994,
    "bob":1506050580,
    "Konoroth":1506051022,
    "Vakaria":1506050846
  },
  "objectData":{
    "0-103":{
      "location":{
        "rotX":0.072664372622967,
        "posY":-63669.02734375,
        "posX":3660.5847167969,
        "posZ":35.607765197754,
        "rotZ":-2.1462767124176,
        "rotY":0
      },
      "refId":"mudcrab",
      "stats":{
        "fatigueCurrent":400,
        "healthBase":15,
        "fatigueBase":400,
        "healthModified":15,
        "fatigueModified":400,
        "magickaModified":5,
        "magickaBase":5,
        "healthCurrent":15,
        "magickaCurrent":5
      }
    },
    "288921-0":{
      "inventory":[{
          "refId":"ingred_marshmerrow_01",
          "count":1,
          "charge":-1
        }],
      "refId":"flora_marshmerrow_01"
    },
    "288914-0":{
      "inventory":[],
      "refId":"flora_marshmerrow_02"
    },
    "288919-0":{
      "inventory":[{
          "refId":"ingred_marshmerrow_01",
          "count":1,
          "charge":-1
        }],
      "refId":"flora_marshmerrow_01"
    },
    "288920-0":{
      "inventory":[{
          "refId":"ingred_marshmerrow_01",
          "count":1,
          "charge":-1
        }],
      "refId":"flora_marshmerrow_02"
    },
    "0-73":{
      "location":{
        "rotX":-0.00063371565192938,
        "posY":-63540.80859375,
        "posX":3719.513671875,
        "posZ":41.000003814697,
        "rotZ":-0.40400505065918,
        "rotY":0
      },
      "refId":"mudcrab",
      "stats":{
        "fatigueCurrent":400,
        "healthBase":15,
        "fatigueBase":400,
        "healthModified":15,
        "fatigueModified":400,
        "magickaModified":5,
        "magickaBase":5,
        "healthCurrent":15,
        "magickaCurrent":5
      }
    },
    "341478-0":{
      "inventory":[],
      "refId":"flora_kreshweed_02"
    },
    "462200-0":{
      "inventory":[{
          "refId":"ingred_pearl_01",
          "count":1,
          "charge":-1
        }],
      "refId":"kollop_03_pearl"
    },
    "0-74":{
      "location":{
        "rotX":-0.0036227321252227,
        "posY":-63072.89453125,
        "posX":2970.0187988281,
        "posZ":18.000123977661,
        "rotZ":-1.3091957569122,
        "rotY":0
      },
      "refId":"mudcrab",
      "stats":{
        "fatigueCurrent":400,
        "healthBase":15,
        "fatigueBase":400,
        "healthModified":15,
        "fatigueModified":400,
        "magickaModified":5,
        "magickaBase":5,
        "healthCurrent":15,
        "magickaCurrent":5
      }
    },
    "288913-0":{
      "inventory":[{
          "refId":"ingred_marshmerrow_01",
          "count":1,
          "charge":-1
        }],
      "refId":"flora_marshmerrow_01"
    },
    "288911-0":{
      "inventory":[{
          "refId":"ingred_marshmerrow_01",
          "count":1,
          "charge":-1
        }],
      "refId":"flora_marshmerrow_02"
    },
    "288908-0":{
      "inventory":[{
          "refId":"ingred_marshmerrow_01",
          "count":1,
          "charge":-1
        }],
      "refId":"flora_marshmerrow_02"
    },
    "3864-0":{
      "inventory":[{
          "refId":"sc_paper plain",
          "count":2,
          "charge":-1
        },{
          "refId":"misc_com_wood_cup_01",
          "count":2,
          "charge":-1
        },{
          "refId":"gold_001",
          "count":4,
          "charge":-1
        }],
      "refId":"barrel_01_pos"
    },
    "333273-0":{
      "inventory":[{
          "refId":"misc_com_redware_vase",
          "count":1,
          "charge":-1
        },{
          "refId":"misc_com_plate_01",
          "count":1,
          "charge":-1
        },{
          "refId":"misc_com_basket_02",
          "count":1,
          "charge":-1
        },{
          "refId":"misc_com_bottle_10",
          "count":1,
          "charge":-1
        },{
          "refId":"misc_com_metal_goblet_01",
          "count":1,
          "charge":-1
        },{
          "refId":"misc_com_pitcher_metal_01",
          "count":1,
          "charge":-1
        },{
          "refId":"gold_001",
          "count":7,
          "charge":-1
        }],
      "refId":"crate_02_random_pos"
    },
    "288915-0":{
      "inventory":[{
          "refId":"ingred_marshmerrow_01",
          "count":1,
          "charge":-1
        }],
      "refId":"flora_marshmerrow_01"
    },
    "0-72":{
      "location":{
        "rotX":-0.35027208924294,
        "posY":-62874.78125,
        "posX":5826.0537109375,
        "posZ":90.285255432129,
        "rotZ":1.8085997104645,
        "rotY":0
      },
      "refId":"mudcrab",
      "stats":{
        "fatigueCurrent":400,
        "healthBase":15,
        "fatigueBase":400,
        "healthModified":15,
        "fatigueModified":400,
        "magickaModified":5,
        "magickaBase":5,
        "healthCurrent":15,
        "magickaCurrent":5
      }
    },
    "0-102":{
      "location":{
        "rotX":-0.00054583698511124,
        "posY":-63135.49609375,
        "posX":4501.0625,
        "posZ":188.74848937988,
        "rotZ":2.0542395114899,
        "rotY":0
      },
      "refId":"mudcrab",
      "stats":{
        "fatigueCurrent":400,
        "healthBase":15,
        "fatigueBase":400,
        "healthModified":15,
        "fatigueModified":400,
        "magickaModified":5,
        "magickaBase":5,
        "healthCurrent":15,
        "magickaCurrent":5
      }
    },
    "333274-0":{
      "inventory":[{
          "refId":"sc_paper plain",
          "count":1,
          "charge":-1
        },{
          "refId":"misc_com_plate_01",
          "count":1,
          "charge":-1
        },{
          "refId":"misc_com_wood_cup_01",
          "count":1,
          "charge":-1
        },{
          "refId":"gold_001",
          "count":3,
          "charge":-1
        },{
          "refId":"misc_com_bottle_10",
          "count":1,
          "charge":-1
        },{
          "refId":"misc_com_bottle_15",
          "count":1,
          "charge":-1
        }],
      "refId":"crate_02_random_pos"
    },
    "288912-0":{
      "inventory":[{
          "refId":"ingred_marshmerrow_01",
          "count":1,
          "charge":-1
        }],
      "refId":"flora_marshmerrow_01"
    },
    "288907-0":{
      "inventory":[{
          "refId":"ingred_marshmerrow_01",
          "count":1,
          "charge":-1
        }],
      "refId":"flora_marshmerrow_01"
    },
    "462192-0":{
      "inventory":[{
          "refId":"ingred_pearl_01",
          "count":1,
          "charge":-1
        }],
      "refId":"kollop_03_pearl"
    },
    "333275-0":{
      "inventory":[{
          "refId":"gold_001",
          "count":5,
          "charge":-1
        },{
          "refId":"misc_com_metal_goblet_01",
          "count":1,
          "charge":-1
        },{
          "refId":"misc_com_plate_01",
          "count":1,
          "charge":-1
        },{
          "refId":"misc_soulgem_petty",
          "count":1,
          "charge":-1
        },{
          "refId":"misc_com_redware_cup",
          "count":1,
          "charge":-1
        },{
          "refId":"misc_com_wood_spoon_02",
          "count":1,
          "charge":-1
        }],
      "refId":"crate_02_random_pos"
    },
    "288910-0":{
      "inventory":[{
          "refId":"ingred_marshmerrow_01",
          "count":1,
          "charge":-1
        }],
      "refId":"flora_marshmerrow_01"
    },
    "333272-0":{
      "inventory":[{
          "refId":"sc_paper plain",
          "count":2,
          "charge":-1
        },{
          "refId":"misc_com_wood_spoon_02",
          "count":2,
          "charge":-1
        },{
          "refId":"misc_com_bottle_15",
          "count":1,
          "charge":-1
        },{
          "refId":"gold_001",
          "count":4,
          "charge":-1
        }],
      "refId":"barrel_01_pos"
    },
    "0-104":{
      "location":{
        "rotX":-0.0078292870894074,
        "posY":-62960.34765625,
        "posX":3179.2319335938,
        "posZ":34.363899230957,
        "rotZ":2.2833168506622,
        "rotY":0
      },
      "refId":"mudcrab",
      "stats":{
        "fatigueCurrent":400,
        "healthBase":15,
        "fatigueBase":400,
        "healthModified":15,
        "fatigueModified":400,
        "magickaModified":5,
        "magickaBase":5,
        "healthCurrent":15,
        "magickaCurrent":5
      }
    },
    "288909-0":{
      "inventory":[{
          "refId":"ingred_marshmerrow_01",
          "count":1,
          "charge":-1
        }],
      "refId":"flora_marshmerrow_01"
    }
  },
  "packets":{
    "delete":[],
    "container":["3864-0","288907-0","288908-0","288909-0","288910-0","288911-0","288912-0","288913-0","288914-0","288915-0","288919-0","288920-0","288921-0","333272-0","333273-0","333274-0","333275-0","341478-0","462192-0","462200-0"],
    "equipment":[],
    "place":[],
    "cellChangeTo":[],
    "statsDynamic":["0-72","0-73","0-74","0-102","0-103","0-104"],
    "cellChangeFrom":[],
    "trap":[],
    "actorList":["0-102","0-103","0-104","0-72","0-73","0-74"],
    "position":["0-72","0-73","0-74","0-102","0-103","0-104"],
    "lock":[],
    "doorState":[],
    "state":[],
    "scale":[],
    "spawn":["0-102","0-103","0-104"]
  }
}